pymaopian/__init__.py
pymaopian/common.py
pymaopian/pymaopian.py
pymaopian-0.0.2.dist-info/LICENSE
pymaopian-0.0.2.dist-info/METADATA
pymaopian-0.0.2.dist-info/WHEEL
pymaopian-0.0.2.dist-info/top_level.txt
pymaopian-0.0.2.dist-info/RECORD
